athena_udf/__init__.py
athena_udf/base.py
athena_udf/utils.py
athena_python_udf-0.2.2.dist-info/LICENSE
athena_python_udf-0.2.2.dist-info/METADATA
athena_python_udf-0.2.2.dist-info/WHEEL
athena_python_udf-0.2.2.dist-info/RECORD
