Metadata-Version: 2.1
Name: athena-python-udf
Version: 0.2.2
Summary: Athena User Defined Functions(UDFs) in Python made easy!
Home-page: https://github.com/dbt-athena/athena-python-udf
License: Apache-2.0
Keywords: aws,athena,python,udf,lambda
Author: David Markey
Author-email: david@dmarkey.com
Maintainer: Serhii Dimchenko
Maintainer-email: svdimchenko@gmail.com
Requires-Python: >=3.9,<4.0
Classifier: License :: OSI Approved :: Apache Software License
Classifier: Programming Language :: Python :: 3
Classifier: Programming Language :: Python :: 3.9
Classifier: Programming Language :: Python :: 3.10
Classifier: Programming Language :: Python :: 3.11
Classifier: Programming Language :: Python :: 3.12
Requires-Dist: pyarrow (>=15.0.2,<16.0.0)
Project-URL: Repository, https://github.com/dbt-athena/athena-python-udf
